liquid_earth_api/__init__.py
liquid_earth_api/_version.py
liquid_earth_api/config.py
liquid_earth_api/api/__init__.py
liquid_earth_api/api/le_api.py
liquid_earth_api/api/utils_api.py
liquid_earth_api/core/__init__.py
liquid_earth_api/data/__init__.py
liquid_earth_api/data/le_data_types.py
liquid_earth_api/data/schemas.py
liquid_earth_api/modules/__init__.py
liquid_earth_api/modules/blob_client/__init__.py
liquid_earth_api/modules/blob_client/blob_interface.py
liquid_earth_api/modules/data_converter/__init__.py
liquid_earth_api/modules/data_converter/converter_interface.py
liquid_earth_api/modules/rest_client/__init__.py
liquid_earth_api/modules/rest_client/_links.py
liquid_earth_api/modules/rest_client/_utils.py
liquid_earth_api/modules/rest_client/rest_interface.py
tests/__init__.py
tests/conftest.py
tests/test_le_api_I.py
liquid_earth_api-2024.1.0.dist-info/LICENSE.txt
liquid_earth_api-2024.1.0.dist-info/METADATA
liquid_earth_api-2024.1.0.dist-info/WHEEL
liquid_earth_api-2024.1.0.dist-info/top_level.txt
liquid_earth_api-2024.1.0.dist-info/RECORD
